MANIFEST.in
README.rst
setup.py
docs/HISTORY.txt
docs/LICENSE.txt
emencia/__init__.py
emencia.django.downloader.egg-info/PKG-INFO
emencia.django.downloader.egg-info/SOURCES.txt
emencia.django.downloader.egg-info/dependency_links.txt
emencia.django.downloader.egg-info/entry_points.txt
emencia.django.downloader.egg-info/namespace_packages.txt
emencia.django.downloader.egg-info/not-zip-safe
emencia.django.downloader.egg-info/requires.txt
emencia.django.downloader.egg-info/top_level.txt
emencia/django/__init__.py
emencia/django/downloader/__init__.py
emencia/django/downloader/admin.py
emencia/django/downloader/forms.py
emencia/django/downloader/models.py
emencia/django/downloader/tests.py
emencia/django/downloader/testsettings.py
emencia/django/downloader/urls.py
emencia/django/downloader/views.py
emencia/django/downloader/locale/fr/LC_MESSAGES/django.mo
emencia/django/downloader/locale/fr/LC_MESSAGES/django.po
emencia/django/downloader/templates/base.html
emencia/django/downloader/templates/downloader/base.html
emencia/django/downloader/templates/downloader/notify_friends.txt
emencia/django/downloader/templates/downloader/notify_sender.txt
emencia/django/downloader/templates/downloader/upload.html
emencia/django/downloader/templates/downloader/upload_ok.html