Metadata-Version: 1.0
Name: emencia.django.downloader
Version: 0.1
Summary: Downloader app like dl.free.fr in django
Home-page: http://www.emencia.fr
Author: Philippe Lafaye
Author-email: lafaye@emencia.com
License: GNU Affero General Public License v3
Platform: UNKNOWN
Classifier: Intended Audience :: Developers
Classifier: Operating System :: OS Independent
Classifier: Programming Language :: Python
Classifier: Topic :: Software Development :: Libraries :: Python Modules
Classifier: License :: OSI Approved :: GNU Affero General Public License v3
